httpie_f5_auth
