Metadata-Version: 1.1
Name: httpie-f5-auth
Version: 0.0.6
Summary: F5 BIG-IQ Auth plugin for HTTPie.
Home-page: https://github.com/imecimore/httpie-f5-auth
Author: Ivan Mecimore
Author-email: imecimore@gmail.com
License: MIT
Download-URL: https://github.com/imecimore/httpie-f5-auth
Platform: UNKNOWN
Classifier: Development Status :: 4 - Beta
Classifier: Programming Language :: Python
Classifier: Intended Audience :: Developers
Classifier: Environment :: Plugins
Classifier: License :: OSI Approved :: MIT License
Classifier: Topic :: Internet :: WWW/HTTP
Classifier: Topic :: Utilities
